Metadata-Version: 2.0
Name: odoo9-addon-l10n-es-toponyms
Version: 9.0.1.0.0
Summary: Topónimos españoles
Home-page: https://github.com/OCA/l10n-spain
Author: Spanish Localization Team, ZikZakMedia, Tecnativa, Odoo Community Association (OCA)
Author-email: support@odoo-community.org
License: AGPL-3
Platform: UNKNOWN
Requires-Dist: odoo (<9.1a,>=9.0a)
Requires-Dist: odoo9-addon-base-location-geonames-import
Classifier: Programming Language :: Python :: 2.7
Classifier: Framework :: Odoo
Classifier: License :: OSI Approved :: GNU Affero General Public License v3
